.condarc
.gitignore
LICENSE
README.md
setup.cfg
setup.py
conda-recipe/bld.bat
conda-recipe/build.sh
conda-recipe/meta.yaml
discon/__init__.py
discon/__main__.py
discon/file_content.py
discon.egg-info/PKG-INFO
discon.egg-info/SOURCES.txt
discon.egg-info/dependency_links.txt
discon.egg-info/entry_points.txt
discon.egg-info/pbr.json
discon.egg-info/top_level.txt