Metadata-Version: 1.1
Name: discon
Version: 2.3.4
Summary: distribution to pypi and conda
Home-page: https://github.com/mjirik/discon
Author: Miroslav Jirik
Author-email: miroslav.jirik@gmail.com
License: MIT
Keywords: distribution,conda
Platform: UNKNOWN
Classifier: Development Status :: 3 - Alpha
Classifier: Intended Audience :: Developers
Classifier: Topic :: Scientific/Engineering :: Bio-Informatics
Classifier: License :: OSI Approved :: BSD License
Classifier: Programming Language :: Python :: 2.7
Classifier: Programming Language :: Python :: 3.6
Classifier: Programming Language :: Python :: 3.7
